examples/__init__.py
examples/ad-sponsored.py
examples/bluesheets.py
examples/chatlogs.py
examples/cites-draft.py
examples/document-authors.py
examples/draft-authors.py
examples/draft-references.py
examples/draft-submissions-by-date.py
examples/draft-submissions-from-email.py
examples/draft-submissions.py
examples/drafts-for-person.py
examples/drafts-for-rfc.py
examples/drafts-for-rfcs.py
examples/drafts-for-wg.py
examples/emails-ietf-community.py
examples/emails-per-person.py
examples/fetch-rfcs.py
examples/iesg-processing-time.py
examples/ietf-areas.py
examples/ietf-leadership.py
examples/ietf-list-membership.py
examples/irtf-ipr.py
examples/irtf-states.py
examples/lists.py
examples/mailing-lists.py
examples/modpod.py
examples/non-wg-standards-track-rfcs.py
examples/org-chart.py
examples/person-attendance.py
examples/person-emails.py
examples/person.py
examples/recent-pubreq.py
examples/rfc-affiliations.py
examples/rfc-authors.py
examples/rfc-data.py
examples/rfc-per-year-ietf.py
examples/rfc-per-year.py
examples/rfc-streams.py
examples/rfc-unique-authors.py
examples/role-names.py
examples/uniq-emails-2007.py
examples/uniq-emails-2019.py
examples/uniq-emails-2020.py
examples/uniq-emails-2021.py
examples/uniq-emails.py
examples/wg-chairs.py
examples/wg-conflicts.py
ietfdata/__init__.py
ietfdata/datatracker.py
ietfdata/datatracker_ext.py
ietfdata/mailarchive-new.py
ietfdata/mailarchive.py
ietfdata/mailarchive2.py
ietfdata/mailarchive3.py
ietfdata/py.typed
ietfdata/rfcindex.py
ietfdata-0.8.3.dist-info/LICENSE
ietfdata-0.8.3.dist-info/METADATA
ietfdata-0.8.3.dist-info/WHEEL
ietfdata-0.8.3.dist-info/top_level.txt
ietfdata-0.8.3.dist-info/RECORD
