Metadata-Version: 2.1
Name: ietfdata
Version: 0.8.3
Summary: Access the IETF Data Tracker and RFC Index
Home-page: https://github.com/glasgow-ipl/ietfdata
Author: Colin Perkins
Author-email: Colin Perkins <csp@csperkins.org>
Classifier: Programming Language :: Python :: 3
Classifier: License :: OSI Approved :: BSD License
Classifier: Operating System :: OS Independent
Requires-Python: >=3.13
License-File: LICENSE
Requires-Dist: bs4
Requires-Dist: email_reply_parser
Requires-Dist: imapclient
Requires-Dist: pandas
Requires-Dist: pandas-stubs
Requires-Dist: python-dateutil
Requires-Dist: pydantic
Requires-Dist: pymongo
Requires-Dist: requests
Requires-Dist: requests-cache
Requires-Dist: mypy
Requires-Dist: wheel
Requires-Dist: twine
Requires-Dist: keyring
Requires-Dist: coverage
Requires-Dist: pymongo-stubs
Requires-Dist: types-six
Requires-Dist: types-requests
Requires-Dist: types-python-dateutil
